powerbi/auth.py
powerbi/available_features.py
powerbi/capacities.py
powerbi/client.py
powerbi/dashboards.py
powerbi/dataflow_storage_account.py
powerbi/enums.py
powerbi/groups.py
powerbi/imports.py
powerbi/push_datasets.py
powerbi/reports.py
powerbi/session.py
powerbi/template_apps.py
powerbi/users.py
powerbi/utils.py
python_power_bi-0.1.2.dist-info/LICENSE
python_power_bi-0.1.2.dist-info/METADATA
python_power_bi-0.1.2.dist-info/WHEEL
python_power_bi-0.1.2.dist-info/top_level.txt
python_power_bi-0.1.2.dist-info/RECORD
