Metadata-Version: 2.1
Name: python-power-bi
Version: 0.1.2
Summary: The Unofficial Python API wrapper for the Microsoft Power BI REST API.
Home-page: https://github.com/areed1192/power-bi-python-api.git
Author: Alex Reed
Author-email: coding.sigma@gmail.com
License: UNKNOWN
Platform: UNKNOWN
Classifier: Development Status :: 3 - Alpha
Classifier: Intended Audience :: Developers
Classifier: Intended Audience :: Science/Research
Classifier: Intended Audience :: Financial and Insurance Industry
Classifier: License :: OSI Approved :: MIT License
Classifier: Natural Language :: English
Classifier: Operating System :: OS Independent
Classifier: Programming Language :: Python :: 3.7
Classifier: Programming Language :: Python :: 3.8
Classifier: Topic :: Database
Classifier: Topic :: Education
Classifier: Topic :: Office/Business
Requires-Python: >3.7
Requires-Dist: msal
Requires-Dist: requests
